evervault/__init__.py
evervault/cages_v2.py
evervault/client.py
evervault/crypto/__init__.py
evervault/crypto/client.py
evervault/crypto/curves/__init__.py
evervault/crypto/curves/base.py
evervault/crypto/curves/koblitz.py
evervault/crypto/curves/p256.py
evervault/crypto/version.py
evervault/datatypes/__init__.py
evervault/datatypes/map.py
evervault/enclaves.py
evervault/errors/__init__.py
evervault/errors/error_handler.py
evervault/errors/evervault_errors.py
evervault/http/__init__.py
evervault/http/attestationdoc.py
evervault/http/outboundrelayconfig.py
evervault/http/pcrManager.py
evervault/http/request.py
evervault/http/requesthandler.py
evervault/http/requestintercept.py
evervault/models/__init__.py
evervault/models/cage.py
evervault/services/__init__.py
evervault/services/timeservice.py
evervault/threading/repeatedtimer.py
evervault-5.0.0.dist-info/LICENSE
evervault-5.0.0.dist-info/METADATA
evervault-5.0.0.dist-info/WHEEL
evervault-5.0.0.dist-info/RECORD
